batchee/__init__.py
batchee/harmony/__init__.py
batchee/harmony/cli.py
batchee/harmony/service_adapter.py
batchee/harmony/util.py
batchee/tempo_filename_parser.py
batchee-1.5.2.dist-info/LICENSE
batchee-1.5.2.dist-info/METADATA
batchee-1.5.2.dist-info/WHEEL
batchee-1.5.2.dist-info/entry_points.txt
batchee-1.5.2.dist-info/RECORD
