Metadata-Version: 2.3
Name: batchee
Version: 1.5.2
Summary: Determine how to group together input files into batches for subsequent concatenation
License: Apache License
Keywords: nasa,earthdata,batch
Author: Daniel Kaufman
Author-email: daniel.kaufman@nasa.gov
Requires-Python: >=3.12,<4
Classifier: License :: Other/Proprietary License
Classifier: Programming Language :: Python :: 3
Classifier: Programming Language :: Python :: 3.12
Classifier: Programming Language :: Python :: 3.13
Provides-Extra: dev
Requires-Dist: coverage (>=7.8.0) ; extra == "dev"
Requires-Dist: harmony-service-lib (>=2.0.0)
Requires-Dist: mypy (>=1.15.0) ; extra == "dev"
Requires-Dist: pytest (>=8.3.5) ; extra == "dev"
Requires-Dist: pytest-cov (>=6.1.1) ; extra == "dev"
Requires-Dist: ruff (>=0.11.8) ; extra == "dev"
Project-URL: Bug Tracker, https://github.com/nasa/batchee/issues
Project-URL: Changelog, https://github.com/nasa/batchee/blob/main/CHANGELOG.md
Project-URL: Repository, https://github.com/nasa/batchee
